factoring_ruc/__init__.py
factoring_ruc/consulta_ruc.py
FactoringRuc-1.0.1.dist-info/METADATA
FactoringRuc-1.0.1.dist-info/WHEEL
FactoringRuc-1.0.1.dist-info/top_level.txt
FactoringRuc-1.0.1.dist-info/RECORD
