Metadata-Version: 2.1
Name: FactoringRuc
Version: 1.0.1
Summary: Eliges un tipo de documento y realizas la consulta obteniendo los resultados de sunat.
Home-page: https://github.com/leasingtotal/consulta-ruc
Author: Jose Sakuda
Author-email: jsakuda@josesakuda.com.de
License: GNU General Public License v3.0
Platform: UNKNOWN
Requires-Python: >=3.6
Requires-Dist: requests
